Metadata-Version: 2.1
Name: factorial-aivn-023
Version: 0.1.0
Summary: 
Author: Phuc Trinh
Author-email: trinhduyphuc98@gmail.com
Requires-Python: >=3.10,<4.0
Classifier: Programming Language :: Python :: 3
Classifier: Programming Language :: Python :: 3.10
Classifier: Programming Language :: Python :: 3.11
Classifier: Programming Language :: Python :: 3.12
Requires-Dist: pytest (>=8.2.0,<9.0.0)
Requires-Dist: streamlit (>=1.34.0,<2.0.0)
